resources/__init__.py
resources/api.py
resources/client.py
resources/exceptions.py
resources/live_streams.py
resources/media.py
resources/playback_ids.py
resources/signing_keys.py
pythonsubbu-0.2.0.dist-info/METADATA
pythonsubbu-0.2.0.dist-info/WHEEL
pythonsubbu-0.2.0.dist-info/top_level.txt
pythonsubbu-0.2.0.dist-info/RECORD
